{"can": 45, "you": 393, "find": 119, "the": 343, "medical": 203, "reports": 285, "how": 157, "help": 150, "me": 199, "what": 377, "does": 89, "it": 171, "mean": 202, "if": 159, "my": 218, "blood": 34, "sugar": 328, "level": 179, "is": 170, "above": 2, "100": 0, "do": 86, "know": 175, "high": 152, "or": 237, "low": 189, "by": 44, "looking": 186, "at": 22, "mammogram": 194, "report": 284, "whether": 380, "am": 14, "risk": 291, "not": 224, "fetch": 118, "show": 308, "test": 340, "want": 369, "to": 351, "see": 303, "give": 131, "from": 124, "history": 153, "please": 250, "documents": 88, "where": 379, "recent": 272, "tests": 342, "ray": 271, "need": 221, "check": 51, "mri": 215, "get": 129, "latest": 178, "results": 286, "access": 3, "online": 234, "provide": 260, "with": 385, "scans": 300, "retrieve": 287, "past": 242, "of": 230, "last": 177, "physical": 246, "examination": 109, "copy": 63, "previous": 257, "doctor": 87, "prescription": 255, "lab": 176, "now": 226, "surgery": 333, "vaccination": 361, "records": 275, "bring": 42, "ct": 67, "scan": 299, "cardiology": 47, "charts": 50, "year": 390, "pull": 264, "up": 360, "covid": 66, "review": 288, "levels": 180, "month": 210, "hospital": 156, "visit": 365, "details": 77, "display": 85, "ultrasound": 359, "view": 363, "diagnostic": 78, "for": 123, "health": 142, "could": 64, "notes": 225, "years": 391, "improve": 164, "should": 307, "stay": 320, "healthy": 146, "diet": 79, "feel": 117, "stressed": 324, "any": 17, "advice": 8, "sure": 332, "getting": 130, "enough": 103, "sleep": 311, "tips": 349, "exercise": 110, "routine": 295, "tired": 350, "often": 231, "best": 32, "way": 372, "lose": 187, "weight": 375, "much": 216, "water": 371, "drink": 92, "daily": 69, "suggest": 330, "good": 136, "breakfast": 40, "start": 319, "exercising": 112, "regularly": 280, "are": 19, "benefits": 31, "yoga": 392, "cope": 62, "stress": 323, "better": 33, "eat": 96, "lunch": 190, "have": 139, "recommend": 273, "workout": 388, "plan": 247, "active": 5, "during": 95, "day": 70, "some": 316, "staying": 321, "quit": 269, "smoking": 312, "trying": 358, "healthier": 144, "suggestions": 331, "fitness": 120, "goals": 134, "nutrients": 227, "meditate": 205, "motivated": 214, "dinner": 82, "boost": 38, "immune": 161, "system": 335, "make": 193, "eating": 97, "balanced": 27, "meals": 201, "running": 296, "marathon": 198, "sick": 309, "manage": 195, "work": 386, "life": 181, "balance": 26, "signs": 310, "dehydration": 73, "headache": 141, "drinking": 93, "stop": 322, "procrastinating": 258, "anxiety": 16, "rid": 290, "negative": 222, "thoughts": 347, "snack": 313, "more": 211, "energetic": 101, "jogging": 172, "deal": 71, "insomnia": 166, "focused": 121, "overtraining": 240, "mental": 207, "stretch": 325, "avoid": 24, "injuries": 165, "while": 381, "time": 348, "on": 233, "track": 353, "healthiest": 145, "overall": 239, "relief": 282, "techniques": 337, "heart": 147, "rate": 270, "pressure": 256, "dietitian": 80, "allergy": 12, "reduce": 277, "cholesterol": 54, "immunization": 162, "intensity": 168, "interval": 169, "training": 354, "glucose": 132, "monitoring": 209, "vision": 364, "tell": 338, "about": 1, "yourself": 395, "cure": 68, "cancer": 46, "rohit": 293, "going": 135, "coffee": 55, "books": 37, "they": 345, "sexy": 306, "go": 133, "hell": 148, "like": 182, "take": 336, "suger": 329, "dont": 91, "brain": 39, "mind": 208, "working": 387, "kashmir": 173, "was": 370, "munnar": 217, "been": 29, "hi": 151, "hello": 149, "everything": 107, "ok": 232, "love": 188, "too": 352, "sex": 305, "your": 394, "breast": 41, "after": 9, "treatment": 355, "think": 346, "very": 362, "why": 383, "who": 382, "salam": 297, "namaste": 219, "alu": 13, "bade": 25, "saste": 298, "erectile": 105, "disfunction": 84, "well": 376, "soon": 317, "comming": 59, "coming": 58, "morning": 212, "afternoon": 10, "colonoscopy": 57, "pathology": 243, "study": 327, "ophthalmology": 236, "most": 213, "dermatology": 76, "consultation": 61, "neurology": 223, "evaluation": 106, "pulmonary": 265, "function": 125, "gastroenterology": 126, "endoscopy": 100, "rheumatology": 289, "imaging": 160, "medication": 204, "list": 183, "family": 116, "operative": 235, "discharge": 83, "instructions": 167, "progress": 259, "appointment": 18, "emergency": 99, "room": 294, "therapy": 344, "occupational": 229, "speech": 318, "psychotherapy": 263, "psychiatric": 262, "reconciliation": 274, "advance": 7, "care": 48, "planning": 248, "living": 184, "will": 384, "durable": 94, "power": 253, "attorney": 23, "healthcare": 143, "proxy": 261, "organ": 238, "donation": 90, "registration": 278, "genetic": 127, "testing": 341, "prenatal": 254, "postpartum": 251, "pediatric": 244, "adolescent": 6, "geriatric": 128, "assessment": 21, "palliative": 241, "hospice": 155, "home": 154, "long": 185, "term": 339, "rehabilitation": 281, "case": 49, "management": 196, "social": 315, "nutritional": 228, "wound": 389, "ecg": 98, "exam": 108, "child": 53, "dental": 75, "checkup": 52, "bone": 36, "density": 74, "screening": 302, "vitamin": 366, "deficiency": 72, "having": 140, "hair": 138, "fall": 114, "whats": 378, "body": 35, "count": 65, "importance": 163, "maintaining": 192, "ensure": 104, "hydrated": 158, "habit": 137, "walk": 368, "meditating": 206, "build": 43, "sustainable": 334, "quality": 266, "relieve": 283, "exhausted": 113, "all": 11, "managing": 197, "foods": 122, "digestion": 81, "naturally": 220, "risks": 292, "plant": 249, "based": 28, "keep": 174, "energy": 102, "recover": 276, "quickly": 268, "cold": 56, "snacks": 314, "try": 357, "quick": 267, "trouble": 356, "falling": 115, "asleep": 20, "achieve": 4, "vitamins": 367, "exercises": 111, "beginners": 30, "ways": 373, "self": 304, "confidence": 60, "weekly": 374, "meal": 200, "regular": 279, "stretching": 326, "and": 15, "personal": 245, "posture": 252, "screen": 301, "maintain": 191}